Metadata-Version: 2.1
Name: resourcesManager
Version: 4.0
Summary: Criação de resources mais rápida
Author: Luan Soares
Author-email: piitszkdev@outlook.com
License: MIT License
Keywords: fivem
License-File: LICENSE
